README
setup.py
shinkenplugins/__init__.py
shinkenplugins.plugins.graphite_api.egg-info/PKG-INFO
shinkenplugins.plugins.graphite_api.egg-info/SOURCES.txt
shinkenplugins.plugins.graphite_api.egg-info/dependency_links.txt
shinkenplugins.plugins.graphite_api.egg-info/entry_points.txt
shinkenplugins.plugins.graphite_api.egg-info/namespace_packages.txt
shinkenplugins.plugins.graphite_api.egg-info/requires.txt
shinkenplugins.plugins.graphite_api.egg-info/top_level.txt
shinkenplugins/plugins/__init__.py
shinkenplugins/plugins/graphite_api/__init__.py
shinkenplugins/plugins/graphite_api/graphite_api.py